{"book": {"publisher": "Harper Perennial Modern Classics", "synopsis": "One of Gabriel García Márquez"s most intricate and ambitious works, The Autumn of the Patriarch is a brilliant tale of a Caribbean tyrant and the corruption of power.<br/>From charity to deceit, benevolence to violence, fear of God to extreme cruelty, the dictator of The Autumn of the Patriarch embodies the best and the worst of human nature. Gabriel García Márquez, the renowned master of magical realism, vividly portrays the dying tyrant caught in the prison of his own dictator-ship. Employing an innovative, dreamlike style, and overflowing with symbolic descriptions, the novel transports the reader to a world that is at once fanciful and real.", "language": "en", "image": "https: //images.isbndb.com/covers/28/60/9780060882860.jpg", "title_long": "The Autumn of the Patriarch", "edition": "~", "dimensions": "Height: 8 Inches, Length: 5.31 Inches, Weight: 0.52 Pounds, Width: 0.65 Inches", "dimensions_structured": {"length": {"unit": "inches", "value": 5.31}, "width": {"unit": "inches", "value": 0.65}, "weight": {"unit": "pounds", "value": 0.52}, "height": {"unit": "inches", "value": 8}}, "pages": 255, "date_published": "2006-03-14", "subjects": ["Literature & Fiction', 'Genre Fiction', 'Historical', 'World Literature', 'Caribbean & Latin American', 'United States', 'Contemporary', 'Literary', 'Science Fiction & Fantasy', 'Fantasy', 'Magical Realism', 'Self Service', 'Custom Stores'], 'authors": ["Gabriel Garcia Marquez'], 'title": "The Autumn of the Patriarch", "isbn13": "9780060882860", "msrp": 13.99, 'binding": "Paperback", "isbn": "0060882867", "isbn10": "0060882867"}}