{"book": {"publisher": "HarperOne", "synopsis": "A concise and up-to-date guide to the history, teachings, and practice of Buddhism by two luminaries in the field of world religions.", "language": "en", "image": "https: //images.isbndb.com/covers/06/73/9780060730673.jpg", "title_long": "Buddhism: A Concise Introduction", "edition": "Reprint", "dimensions": "Height: 0.63 Inches, Length: 7.98 Inches, Weight: 0.440924524 Pounds, Width: 5.34 Inches", "dimensions_structured": {'length": {"unit": "inches", "value": 7.98}, "width": {"unit": "inches", "value": 5.34}, "weight": {"unit": "pounds", "value": 0.440924524}, "height": {"unit": "inches", "value": 0.63}}, "pages": 256, "date_published": "2004-12-14", "subjects": ["Religion & Spirituality', 'Buddhism', 'History', 'Religious Studies', 'Comparative Religion', 'Politics & Social Sciences', 'Social Sciences', 'Politics & Government', 'International & World Politics'], 'authors": ["Huston Smith', 'Philip Novak'], 'title": "Buddhism: A Concise Introduction", "isbn13": "9780060730673", "msrp": 12.99, "binding": "Paperback", "related": {"ePub": "006173974X"}, "isbn": "0060730676", "isbn10": "0060730676", "other_isbns": [{'isbn": "9780061739743", "binding": "print"}]}}