{"book": {"publisher": "HarperCollins", "synopsis": "In the great green room, there"s one quiet old lady whispering hush...<br/>Two little kittens...<br/>Three little bears...<br/>Count all the way to one hundred stars and look for the familiar things from Goodnight Moon, everyone"s favorite bedtime story.", 'language": "en", "image": "https: //images.isbndb.com/covers/59/35/9780061125935.jpg", "title_long": "Goodnight Moon 123: A Counting Book", "edition": "First Edition", "dimensions": "Height: 8.5 Inches, Length: 10 Inches, Weight: 0.75 Pounds, Width: 0.25 Inches", "dimensions_structured": {"length": {"unit": "inches", "value": 10}, "width": {"unit": "inches", "value": 0.25}, "weight": {"unit": "pounds", "value": 0.75}, "height": {"unit": "inches", "value": 8.5}}, "pages": 32, "date_published": "2007-07-01", "subjects": ["Children's Books', 'Classics'], 'authors": ["Margaret Wise Brown'], 'title": "Goodnight Moon 123: A Counting Book", "isbn13": "9780061125935", "msrp": 16.99, 'binding": "Hardcover", "isbn": "0061125938", "isbn10": "0061125938"}}