{"book": {"publisher": "Harcourt Childrens Books", "synopsis": "Poor Anne Hathaway is still living with her callous stepmother, and her prospects for marriage and a home of her own are becoming grim. However, she can\x92t seem to get charismatic Will Shakespeare out of her mind--even though he is much too young for her. But then one day Will impulsively kisses his childhood friend Anne, changing the course of their lives forever.<br/>Here is the story of the childhoods of and tumultuous romance between the boy who became the world\x92s most famous playwright and the spirited farmer\x92s daughter who became his wife. Carolyn Meyer has delivered a riveting historical tale about love, family, the pursuit of one\x92s dreams--and the price one pays for each.", "language": "en", "image": "https://images.isbndb.com/covers/45/19/9780152054519.jpg", "title_long": "Loving Will Shakespeare", "edition": "First Edition", "dimensions": "Height: 8.75 Inches, Length: 6 Inches, Weight: 0.85 Pounds, Width: 0.75 Inches", "dimensions_structured": {'length": {"unit": "inches", "value": 6}, "width": {"unit": "inches", "value": 0.75}, "weight": {"unit": "pounds", "value": 0.85}, "height": {"unit": "inches", "value": 8.75}}, "pages": 265, "date_published": "2006", "subjects": ["Teen & Young Adult', 'Literature & Fiction', 'Social & Family Issues', 'Historical Fiction', 'Europe', 'Romance', 'Historical'], 'authors": ['Carolyn Meyer'], 'title": "Loving Will Shakespeare", "isbn13": "9780152054519", "msrp": "0.00", "binding": "Hardcover", "isbn": "0152054510", "isbn10": "0152054510"}}