{"book": {"publisher": "Little, Brown and Company", "synopsis": "A fascinating exploration, spanning two thousand years, of the central role exotic animals have played in war, diplomacy, and the pomp of rulers and luminaries.", "language": "en", "image": "https://images.isbndb.com/covers/56/57/9780316525657.jpg", "title_long": "The Medici Giraffe", "edition": "1", "dimensions": "Height: 9.38 Inches, Length: 6.34 Inches, Weight: 0.661386786 Pounds, Width: 1.35 Inches", "dimensions_structured": {'length": {"unit": "inches", "value": 6.34}, "width": {"unit": "inches", "value": 1.35}, "weight": {"unit": "pounds", "value": 0.661386786}, "height": {"unit": "inches", "value": 9.38}}, "pages": 432, "date_published": "2006-08-21", "subjects": ["Biographies & Memoirs', 'Leaders & Notable People', 'Political', 'History', 'World', 'Civilization & Culture', 'Engineering & Transportation', 'Engineering', 'Science & Math', 'Agricultural Sciences', 'Animal Husbandry', 'Biological Sciences', 'Animals', 'Zoology', 'Nature & Ecology', 'Fauna'], 'authors": ["Marina Belozerskaya'], 'title": "The Medici Giraffe", "isbn13": "9780316525657", "msrp": 33, "binding": "Hardcover", "isbn": "0316525650", "isbn10": "0316525650", "other_isbns": [{'isbn": "9780316076425", "binding": "saleableprint"}]}}