{"book": {"publisher": "Pearson / Longman", "synopsis": "Extracted from the best-selling Complete Works of Shakespeare, 5/e by David Bevington, The Necessary Shakespeare offers the most comprehensive scholarly apparatus, with the most often taught—necessary—of Shakespeare"s work, creating a truly concise yet complete anthology. This anthology provides extensive introductions to the plays and poems-offering discussion topics, sources for each play, and the stage history of performances. Readers interested in Shakespeare.", "language": "en", "image": "https://images.isbndb.com/covers/25/08/9780321272508.jpg", "title_long": "The Necessary Shakespeare, 2nd Edition", "edition": "2nd", "dimensions": "Height: 9.86 Inches, Length: 7.82 Inches, Weight: 2.92553421674 Pounds, Width: 1.28 Inches", "dimensions_structured": {"length": {"unit": "inches", "value": 7.82}, "width": {"unit": "inches", "value": 1.28}, "weight": {"unit": "pounds", "value": 2.92553421674}, "height": {"unit": "inches", "value": 9.86}}, "pages": 1136, "date_published": "2004-07-17", "subjects": ["Literature & Fiction', 'Dramas & Plays', 'History & Criticism', 'Criticism & Theory', 'Movements & Periods', 'Reference', 'Writing, Research & Publishing Guides', 'Writing', 'Specialty Boutique', 'New, Used & Rental Textbooks'], 'authors": ["William Shakespeare'], 'title": "The Necessary Shakespeare, 2nd Edition", "isbn13": "9780321272508", "msrp": 71.6, 'binding": "Paperback", "isbn": "0321272501", "isbn10": "0321272501"}}