{"book": {"publisher": "Del Rey", "synopsis": "SAKURA AND SYAORAN RETURN!<br/><br/>But they’re not the people you know. Sakura is the princess of Clow—and possessor of a mysterious, misunderstood power that promises to change the world. Syaoran is her childhood friend and leader of the archaeological dig that took his father’s life. They reside in an alternate reality . . . where whatever you least expect can happen—and does. When Sakura ventures to the dig site to declare her love for Syaoran, a puzzling symbol is uncovered—which triggers a remarkable quest. Now Syaoran embarks upon a desperate journey through other worlds—all in the name of saving Sakura.<br/><br/>Includes special extras after the story!", "language": "en", "image": "https://images.isbndb.com/covers/05/77/9780345470577.jpg", "title_long": "Tsubasa: Reservoir Chronicle, Vol. 1", "dimensions": "Height: 7.5 Inches, Length: 4.75 Inches, Weight: 0.5 Pounds, Width: 0.75 Inches", "dimensions_structured": {'length": {"unit": "inches", "value": 4.75}, "width": {"unit": "inches", "value": 0.75}, "weight": {"unit": "pounds", "value": 0.5}, "height": {"unit": "inches", "value": 7.5}}, "pages": 208, "date_published": "2004-04-27", "subjects": ["Comics & Graphic Novels', 'Manga', 'Fantasy', 'Science Fiction', 'Romance', 'Science Fiction & Fantasy', 'Teen & Young Adult', 'Literature & Fiction'], 'authors": ["Clamp'], 'title": "Tsubasa: Reservoir Chronicle, Vol. 1", "isbn13": "9780345470577", "msrp": 10.95, 'binding": "Paperback", "isbn": "0345470575", "isbn10": "0345470575"}}