{"book": {"publisher": "Silhouette", "synopsis": "Fiction: romance", "language": "en", "image": "https://images.isbndb.com/covers/31/60/9780373073160.jpg", "title_long": "Flirting with Danger (Silhouette Intimate Moments, No 316)", "edition": "First Edition", "dimensions": "Weight: 4.75 Pounds", "dimensions_structured": {'weight": {"unit": "pounds", "value": 4.75}}, "pages": 253, "date_published": "1989-11-01", "subjects": ["Romance', 'Contemporary'], 'authors": ['Linda Turner'], 'title": "Flirting with Danger (Silhouette Intimate Moments, No 316)", "isbn13": "9780373073160", "msrp": "0.00", "binding": "Mass Market Paperback", "isbn": "037307316X", "isbn10": "037307316X"}}