{"book": {"publisher": "Berkley Books", "synopsis": "A seductive and mesmerizing story of obsessive love from the New York Times bestselling author of The Rules of Magic.<br/><br/>After nineteen years in California, March Murray returns to the small Massachusetts town where she grew up. For all this time, March has been avoiding her own troubled history, but when she encounters Hollis—the boy she loved so desperately, the man who has never forgotten her—the past collides with the present as their reckless love is reignited. This dark romantic tale asks whether it is possible to survive a love that consumes you completely. The answers March Murray discovers are both heartbreaking and wise, as complex as they are devastating—for in heaven and in our dreams, love is simple and glorious. But it is something altogether different here on earth...", "language": "en", "image": "https://images.isbndb.com/covers/96/98/9780425169698.jpg", "title_long": "Here on Earth (Oprah"s Book Club)", "edition": "Reprint", "dimensions": "Height: 6.7 Inches, Length: 4.2 Inches, Weight: 0.41005980732 Pounds, Width: 0.9 Inches", "dimensions_structured": {"length": {"unit": "inches", "value": 4.2}, "width": {"unit": "inches", "value": 0.9}, "weight": {"unit": "pounds", "value": 0.41005980732}, "height": {"unit": "inches", "value": 6.7}}, "pages": 309, "date_published": "1999-07-01", "subjects": ["Literature & Fiction', 'Genre Fiction', 'Family Life', 'Women's Fiction', 'Domestic Life', 'Mothers & Children', 'Contemporary', 'Romance', 'Self Service', 'Custom Stores'], 'authors": ["Alice Hoffman'], 'title": "Here on Earth (Oprah"s Book Club)", 'isbn13": "9780425169698", "msrp": 8.99, "binding": "Mass Market Paperback", "related": {"Kindle Edition": "1440673241", "ePub": "1440673241"}, "isbn": "0425169693", "isbn10": "0425169693", "other_isbns": [{'isbn": "9781440673245", "binding": "print"}]}}