{"book": {"publisher": "HarperCollins", "synopsis": "Betsy, Tacy, and Tib can"t wait to be ten. After all, getting two numbers in your age is the beginning of growing up—exciting things are bound to happen. And they do! The girls fall in love with the King of Spain, perform in the School Entertainment, and for the first time, go all the way over the Big Hill to Little Syria by themselves. There Betsy, Tacy, and Tib make new friends and learn a thing or two. They learn that new Americans are sometimes the best Americans. And they learn that they themselves wouldn"t want to be anything else.<br/>Ever since their first publication in the 1940s, the Betsy-Tacy stories have been loved by each generation of young readers.", 'language": "en", "image": "https: //images.isbndb.com/covers/09/92/9780064400992.jpg", "title_long": "Betsy and Tacy Go Over the Big Hill (Betsy-Tacy, 3)", "edition": "Reissue", "dimensions": "Height: 7.65 Inches, Length: 5.2 Inches, Weight: 0.28 Pounds, Width: 0.5 Inches", "dimensions_structured": {"length": {"unit": "inches", "value": 5.2}, "width": {"unit": "inches", "value": 0.5}, "weight": {"unit": "pounds", "value": 0.28}, "height": {"unit": "inches", "value": 7.65}}, "pages": 192, "date_published": "2000-04-05", "subjects": ["Children's Books', 'Growing Up & Facts of Life', 'Fiction', 'Friendship, Social Skills & School Life', 'Literature & Fiction', 'Historical Fiction', 'Self Service', 'Custom Stores'], 'authors": ["Maud Hart Lovelace'], 'title": "Betsy and Tacy Go Over the Big Hill (Betsy-Tacy, 3)", "isbn13": "9780064400992", "msrp": 6.28, "binding": "Paperback", "related": {"ePub": "006199829X"}, "isbn": "0064400999", "isbn10": "0064400999", "other_isbns": [{'isbn": "9780061998294", "binding": "print"}]}}