{"book": {"publisher": "Vintage Books USA", "synopsis": "Deception", "language": "en", "image": "https: //images.isbndb.com/covers/19/00/9780099801900.jpg", "title_long": "Deception", "dimensions": "Height: 7.79526 Inches, Length: 5.07873 inches, Weight: 0.18 Pounds, Width: 0.51181 inches", "dimensions_structured": {'length": {"unit": "inches", "value": 5.07873}, "width": {"unit": "inches", "value": 0.51181}, "weight": {"unit": "pounds", "value": 0.18}, "height": {"unit": "inches", "value": 7.79526}}, "pages": 208, "date_published": "1998", "subjects": ["Literature & Fiction', 'Literary'], 'authors": ["Philip Roth'], 'title": "Deception", "isbn13": "9780099801900", "msrp": 18.95, 'binding": "Paperback", "isbn": "0099801906", "isbn10": "0099801906"}}