{"book": {"publisher": "Applause Theatre & Cinema Books", "synopsis": "Contents: Marathon Man • Butch Cassidy and the Sundance Kid • The Princess Bride • Misery.", "language": "en", "image": "https://images.isbndb.com/covers/19/89/9781557831989.jpg", "title_long": "William Goldman - Four Screenplays (Applause Books)", "edition": "1", "dimensions": "x, 492 p. ; 25 cm.", "dimensions_structured": {'length": {"unit": "mm", "value": 162}, "width": {"unit": "mm", "value": 32}, "weight": {"unit": "g", "value": 889}, "height": {"unit": "mm", "value": 241}}, "pages": 518, "date_published": "2000", "subjects": ["Arts & Photography', 'Performing Arts', 'Theater', 'Music', 'Songbooks', 'Humor & Entertainment', 'Movies', 'Screenplays', 'Screenwriting', 'Kindle Store', 'Categories', 'Kindle eBooks'], 'authors": ['William Goldman'], 'title": "William Goldman - Four Screenplays (Applause Books)", "isbn13": "9781557831989", "msrp": "0.00", "binding": "Kindle Edition", "isbn": "155783198X", "isbn10": "155783198X"}}